[ {
  "username" : "marko88",
  "password" : "lozinka",
  "name" : "Marko",
  "surname" : "Marković",
  "gender" : "MALE",
  "typeOfUser" : "ADMIN",
  "blocked" : false
}, {
  "username" : "zarko65",
  "password" : "sifra789",
  "name" : "Žarko",
  "surname" : "Žarkić",
  "gender" : "MALE",
  "typeOfUser" : "ADMIN",
  "blocked" : false
}, {
  "username" : "zaregoci",
  "password" : "123",
  "name" : "Zare",
  "surname" : "Zaric",
  "gender" : "MALE",
  "typeOfUser" : "HOST",
  "blocked" : true
}, {
  "username" : "mare",
  "password" : "111",
  "name" : "Mare",
  "surname" : "Maric",
  "gender" : "MALE",
  "typeOfUser" : "HOST",
  "blocked" : true
}, {
  "username" : "dara",
  "password" : "111",
  "name" : "Dara",
  "surname" : "Daric",
  "gender" : "FEMALE",
  "typeOfUser" : "HOST",
  "blocked" : true
}, {
  "username" : "55",
  "password" : "22",
  "name" : "bhbj",
  "surname" : "hkjhk",
  "gender" : "MALE",
  "typeOfUser" : "HOST",
  "blocked" : true
}, {
  "username" : "gaga998",
  "password" : "gaga",
  "name" : "Dragana",
  "surname" : "Carapic",
  "gender" : "FEMALE",
  "typeOfUser" : "HOST",
  "blocked" : false
}, {
  "username" : "pero123",
  "password" : "sifra123",
  "name" : "Pera",
  "surname" : "Perić",
  "gender" : "MALE",
  "typeOfUser" : "GUEST",
  "blocked" : true
}, {
  "username" : "mika789",
  "password" : "sifra789",
  "name" : "Mika",
  "surname" : "Mikić",
  "gender" : "MALE",
  "typeOfUser" : "GUEST",
  "blocked" : true
}, {
  "username" : "mara",
  "password" : "maramica",
  "name" : "Maraica",
  "surname" : "Marić",
  "gender" : "FEMALE",
  "typeOfUser" : "GUEST",
  "blocked" : true
}, {
  "username" : "marko",
  "password" : "marko",
  "name" : "Marko",
  "surname" : "Kraljevic",
  "gender" : "MALE",
  "typeOfUser" : "GUEST",
  "blocked" : true
}, {
  "username" : "darka",
  "password" : "1234",
  "name" : "Dara",
  "surname" : "Daric",
  "gender" : "FEMALE",
  "typeOfUser" : "GUEST",
  "blocked" : true
}, {
  "username" : "sladja97",
  "password" : "sladja",
  "name" : "Sladja",
  "surname" : "Savkovic",
  "gender" : "FEMALE",
  "typeOfUser" : "GUEST",
  "blocked" : false
}, {
  "username" : "dragan1996",
  "password" : "dragan",
  "name" : "Dragan",
  "surname" : "Dragic",
  "gender" : "MALE",
  "typeOfUser" : "HOST",
  "blocked" : false
}, {
  "username" : "labilna",
  "password" : "labilna",
  "name" : "Ana",
  "surname" : "Nikolić",
  "gender" : "FEMALE",
  "typeOfUser" : "GUEST",
  "blocked" : false
} ]